complexitty/__init__.py
complexitty/__main__.py
complexitty/commands/__init__.py
complexitty/commands/colouring.py
complexitty/commands/main.py
complexitty/commands/navigation.py
complexitty/commands/plotting.py
complexitty/complexitty.py
complexitty/data/__init__.py
complexitty/data/config.py
complexitty/data/locations.py
complexitty/mandelbrot/__init__.py
complexitty/mandelbrot/calculator.py
complexitty/mandelbrot/colouring.py
complexitty/mandelbrot/widget.py
complexitty/providers/__init__.py
complexitty/providers/main.py
complexitty/py.typed
complexitty/screens/__init__.py
complexitty/screens/main.py
complexitty-1.0.0.dist-info/WHEEL
complexitty-1.0.0.dist-info/entry_points.txt
complexitty-1.0.0.dist-info/METADATA
complexitty-1.0.0.dist-info/RECORD
