Metadata-Version: 2.4
Name: complexitty
Version: 1.0.0
Summary: A simple Mandelbrot Set explorer for the terminal
Keywords: terminal,tui,chui,mandelbrot,fractal,maths
Author: Dave Pearson
Author-email: Dave Pearson <davep@davep.org>
License-Expression: GPL-3.0-or-later
Classifier: Environment :: Console
Classifier: Development Status :: 5 - Production/Stable
Classifier: Intended Audience :: Education
Classifier: Intended Audience :: End Users/Desktop
Classifier: Intended Audience :: Science/Research
Classifier: Operating System :: OS Independent
Classifier: Programming Language :: Python :: 3.10
Classifier: Programming Language :: Python :: 3.11
Classifier: Programming Language :: Python :: 3.12
Classifier: Programming Language :: Python :: 3.13
Classifier: Programming Language :: Python :: 3.14
Classifier: Topic :: Education
Classifier: Topic :: Games/Entertainment
Classifier: Topic :: Terminals
Classifier: Topic :: Scientific/Engineering :: Mathematics
Classifier: Topic :: Scientific/Engineering :: Visualization
Classifier: Typing :: Typed
Requires-Dist: textual>=3.1.0
Requires-Dist: textual-enhanced>=0.13.0
Requires-Dist: textual-canvas>=0.3.0
Requires-Dist: xdg-base-dirs>=6.0.2
Requires-Python: >=3.10
Project-URL: Discussions, https://github.com/davep/complexitty/discussions
Project-URL: Documentation, https://complexitty.davep.dev/
Project-URL: Homepage, https://complexitty.davep.dev/
Project-URL: Issues, https://github.com/davep/complexitty/issues
Project-URL: Repository, https://github.com/davep/complexitty
Project-URL: Source, https://github.com/davep/complexitty
